calcpkg/__init__.py
calcpkg/geometry.py
calcpkg/operation.py
shin_test-1.0.0.1.dist-info/METADATA
shin_test-1.0.0.1.dist-info/WHEEL
shin_test-1.0.0.1.dist-info/top_level.txt
shin_test-1.0.0.1.dist-info/RECORD
