Metadata-Version: 2.1
Name: shin-test
Version: 1.0.0.1
Summary: Test Package for two modules
Home-page: https://anespart1.tistory.com
Author: Daeyong Shin
Author-email: anespart1@gmail.com
License: MIT
Platform: UNKNOWN
Requires-Python: >=3
